message_prototypes/__init__.py
message_prototypes/base_message.py
message_prototypes/exceptions/__init__.py
message_prototypes/exceptions/missing_model_exception.py
message_prototypes/pipe_messages/__init__.py
message_prototypes/pipe_messages/action_path_message.py
message_prototypes/pipe_messages/auth_message.py
message_prototypes/pipe_messages/request_extra_message.py
message_prototypes/pipe_messages/request_message.py
message_prototypes/pipe_messages/response_message.py
py_message_prototypes-0.2.1.dist-info/LICENSE
py_message_prototypes-0.2.1.dist-info/METADATA
py_message_prototypes-0.2.1.dist-info/WHEEL
py_message_prototypes-0.2.1.dist-info/top_level.txt
py_message_prototypes-0.2.1.dist-info/zip-safe
py_message_prototypes-0.2.1.dist-info/RECORD
