Metadata-Version: 2.1
Name: py-message-prototypes
Version: 0.2.1
Summary: Prototype objects for messaging and datapipes
Home-page: https://github.com/agratoth/py-message-prototypes
Maintainer: Anton Berdnikov
Maintainer-email: agratoth@yandex.ru
License: UNKNOWN
Platform: UNKNOWN
Classifier: License :: OSI Approved :: MIT License
Classifier: Operating System :: OS Independent
Classifier: Programming Language :: Python
Classifier: Programming Language :: Python :: 3.8
Classifier: Programming Language :: Python :: 3.9
Classifier: Topic :: Software Development :: Object Brokering
Requires-Python: >=3.8
